{
  "common": {
    "name": "wifilight",
    "version": "2.0.1",
    "news": {
      "2.0.1": {
        "en": "Corrected error with array comparison\nAdded tests",
        "de": "Fehler behoben mit Array-Vergleich\nZusätzliche Tests",
        "ru": "Исправленная ошибка с сопоставлением массива\nДобавленные испытания",
        "pt": "Erro corrigido com comparação de array\nTestes adicionados",
        "nl": "Gecorrigeerde fout met arrayvergelijking\nToegevoegde tests",
        "fr": "Erreur corrigée avec comparaison de tableau\nEssais ajoutés",
        "it": "Errore corretto con confronto array\nProve aggiuntive",
        "es": "Error corregido con comparación de array\nPruebas adicionales",
        "pl": "Skorygowany błąd z porównywaniem tablic\nDodano badania",
        "uk": "Виправлена помилка з порівнянням масиву\nДодані тести",
        "zh-cn": "与数组比较校正错误\n添加的测试"
      },
      "2.0.0": {
        "en": "The adapter was completely refactored\nAdded compact mode\nJSON config GUI added",
        "de": "Der Adapter wurde komplett überarbeitet\nKompakter Modus\nJSON config GUI hinzugefügt",
        "ru": "Адаптер был полностью рефакторирован\nДобавить компактный режим\nJSON config GUI добавлен",
        "pt": "O adaptador foi completamente refactored\nAdicionado modo compacto\nJSON config GUI adicionado",
        "nl": "De adapter was volledig gerefactoreerd\nCompacte modus toegevoegd\nJSON config GUI toegevoegd",
        "fr": "L'adaptateur a été complètement refacturé\nAjout du mode compact\nJSON config GUI ajouté",
        "it": "L'adattatore è stato completamente rifatto\nAggiunta modalità compatta\nJSON config GUI aggiunto",
        "es": "El adaptador fue completamente refactorizado\nModo compacto\nJSON config GUI agregó",
        "pl": "Adapter został całkowicie zrefakturowany\nDodano tryb kompaktowy\nDodano GUI konfiguracyjny JSON",
        "uk": "Адаптер повністю рефакторований\nДодано компактний режим\nJSON config GUI додано",
        "zh-cn": "适配器已完全重构\n添加紧凑模式\n添加 JSON 配置图形界面"
      },
      "1.3.5": {
        "en": "Formatting of the code",
        "de": "Formatierung des Codes",
        "ru": "Форматирование кода",
        "pt": "Formatação do código",
        "nl": "Opmaak van de code",
        "fr": "Formatage du code",
        "it": "Formattazione del codice",
        "es": "Formato del código",
        "pl": "Formatowanie kodu",
        "uk": "Форматування коду",
        "zh-cn": "代码的格式"
      },
      "1.3.3": {
        "en": "Just renamed some functions",
        "de": "Nur einige Funktionen umbenannt",
        "ru": "Просто переименовали некоторые функции",
        "pt": "Apenas renomeado algumas funções",
        "nl": "Een aantal functies hernoemd",
        "fr": "Juste rebaptisé certaines fonctions",
        "it": "Solo rinominato alcune funzioni",
        "es": "Sólo renombra algunas funciones",
        "pl": "Po prostu zmieniłem nazwę kilku funkcji",
        "uk": "Просто перейменуйте деякі функції",
        "zh-cn": "刚刚重新命名了一些功能"
      },
      "1.3.2": {
        "en": "files section has been fixed",
        "de": "dateien abschnitt wurde behoben",
        "ru": "раздел файлов был исправлен",
        "pt": "seção de arquivos foi corrigido",
        "nl": "bestandssectie is hersteld",
        "fr": "la section fichiers a été corrigée",
        "it": "la sezione file è stata fissata",
        "es": "sección de archivos ha sido fijo",
        "pl": "sekcja plików została naprawiona",
        "uk": "розділ файлів було виправлено",
        "zh-cn": "文件区域已固定"
      },
      "1.3.1": {
        "en": "Added ignorance of acknowledgement messages for on/off commands\nrefactoring",
        "de": "Unwissenheit von Quittungsnachrichten für on/off-Befehle hinzugefügt\nrefaktor",
        "ru": "Добавлено невежество в отношении сообщений о признании для команд on/off\nрефакторинг",
        "pt": "Adicionado ignorância de mensagens de reconhecimento para comandos on/off\nrefactoring",
        "nl": "Toegevoegd onwetendheid van bevestigingsberichten voor aan/uit commando's\nrefactoring",
        "fr": "Ajout de l'ignorance des messages de reconnaissance pour les commandes on/off\nrefactoration",
        "it": "Aggiunta ignoranza dei messaggi di riconoscimento per i comandi on/off\nrefactoring",
        "es": "Añadido ignorancia de los mensajes de reconocimiento para comandos on/off\nrefactoring",
        "pl": "Dodano ignorancję komunikatów o potwierdzeniu dla poleceń on / off\nrefaktoring",
        "uk": "Додано ігнорування повідомлень про видачу/вимкнення\nрефакторинг",
        "zh-cn": "对打开/关闭命令的识别消息无知\n正在重构"
      },
      "1.2.2": {
        "en": "Fix js-controller dependency",
        "de": "Js-controller Abhängigkeit",
        "ru": "Фикс js-контроллер зависимость",
        "pt": "Fix js-controller dependência",
        "nl": "Fix js-controller afhankelijkheid",
        "fr": "Correction de la dépendance de js-controller",
        "it": "Fissare la dipendenza da js-controller",
        "es": "Fijar la dependencia js-controller",
        "pl": "Popraw zależność kontrolera js-",
        "uk": "Виправлення залежності js-controller",
        "zh-cn": "修复js控制器依赖性"
      }
    },
    "titleLang": {
      "en": "WiFi Light",
      "de": "WiFi Light",
      "ru": "WiFi Light",
      "pt": "WiFi Light",
      "nl": "WiFi Light",
      "fr": "WiFi Light",
      "it": "WiFi Light",
      "es": "WiFi Light",
      "pl": "WiFi Light",
      "uk": "WiFi Light",
      "zh-cn": "WiFi Light"
    },
    "desc": {
      "en": "WiFi Light Devices",
      "de": "WiFi-Licht-Geräte",
      "ru": "WiFi Light устройства",
      "uk": "WiFi Light пристрої",
      "pt": "Luz Wi-Fi De Dispositivos",
      "nl": "WiFi-Apparaten Licht",
      "fr": "WiFi Des Appareils Légers",
      "it": "WiFi Luce Di Dispositivi",
      "es": "WiFi De Los Dispositivos De Luz",
      "pl": "Oświetlenie Bezprzewodowy Dostęp Do Internetu",
      "zh-cn": "无线光设备"
    },
    "keywords": [
      "wifilight",
      "lw12",
      "ld382"
    ],
    "licenseInformation": {
      "license": "MIT",
      "type": "free"
    },
    "platform": "Javascript/Node.js",
    "mode": "daemon",
    "icon": "wifilight.png",
    "extIcon": "https://raw.githubusercontent.com/iobroker-community-adapters/iobroker.wifilight/master/admin/wifilight.png",
    "readme": "https://github.com/iobroker-community-adapters/iobroker.wifilight/blob/master/README.md",
    "loglevel": "info",
    "type": "lighting",
    "messagebox": true,
    "enabled": true,
    "compact": true,
    "authors": [
      {
        "name": "soef",
        "email": "soef@gmx.net"
      }
    ],
    "dependencies": [
      {
        "js-controller": ">=5.0.19"
      }
    ],
    "globalDependencies": [
      {
        "admin": ">=6.13.16"
      }
    ],
    "plugins": {
      "sentry": {
        "dsn": "https://65b8526e3ca442739e46753bfaf9a0a9@sentry.iobroker.net/190"
      }
    },
    "adminUI": {
      "config": "json"
    },
    "dataSource": "push",
    "connectionType": "local",
    "tier": 2
  },
  "native": {
    "devices": []
  },
  "instanceObjects": [],
  "objects": []
}
